MANIFEST.in
setup.py
bob/__init__.py
bob/csvutil.py
bob/data_table.py
bob/menu.py
bob/models.py
bob/djid/__init__.py
bob/djid/models.py
bob/djid/util.py
bob/djid/column/__init__.py
bob/djid/static/js/djid.js
bob/djid/static/js/require.js
bob/djid/templates/djid.html
bob/djid/templatetags/__init__.py
bob/djid/templatetags/djid.py
bob/forms/__init__.py
bob/forms/dependency.py
bob/forms/dependency_conditions.py
bob/forms/widgets.py
bob/static/bob.js
bob/static/jquery.js
bob/static/bootstrap/css/bootstrap-responsive.min.css
bob/static/bootstrap/css/bootstrap.css
bob/static/bootstrap/css/bootstrap.min.css
bob/static/bootstrap/css/bs3fake.css
bob/static/bootstrap/css/datepicker.css
bob/static/bootstrap/css/lato.woff
bob/static/bootstrap/img/glyphicons-halflings-white.png
bob/static/bootstrap/img/glyphicons-halflings.png
bob/static/bootstrap/js/bootstrap-datepicker.js
bob/static/bootstrap/js/bootstrap.js
bob/static/bootstrap/js/bootstrap.min.js
bob/templates/bob/dropdown_items.html
bob/templates/bob/field_wrapper.html
bob/templates/bob/form.html
bob/templates/bob/form_as_fieldsets.html
bob/templates/bob/main_menu.html
bob/templates/bob/main_menu_bs3fake.html
bob/templates/bob/menu_item.html
bob/templates/bob/pagination.html
bob/templates/bob/sidebar_menu.html
bob/templates/bob/sidebar_menu_subitems.html
bob/templates/bob/tab_menu.html
bob/templates/bob/tab_menu_bs3fake.html
bob/templates/bob/table_header.html
bob/templatetags/__init__.py
bob/templatetags/bob.py
bob/test_djid/__init__.py
bob/test_djid/manage.py
bob/test_djid/models.py
bob/test_djid/settings.py
bob/test_djid/urls.py
bob/test_djid/views.py
bob/test_djid/wsgi.py
bob/test_djid/tests/__init__.py
bob/test_djid/tests/test_ajax.py
bob/test_djid/tests/test_class.py
bob/test_djid/tests/test_column.py
bob/tests/__init__.py
bob/tests/settings.py
bob/tests/unit/__init__.py
bob/tests/unit/dependencies.py
bob/views/__init__.py
bob/views/bulk_edit.py
bob/views/dependency.py
django_bob.egg-info/PKG-INFO
django_bob.egg-info/SOURCES.txt
django_bob.egg-info/dependency_links.txt
django_bob.egg-info/not-zip-safe
django_bob.egg-info/pbr.json
django_bob.egg-info/requires.txt
django_bob.egg-info/top_level.txt