Metadata-Version: 1.1
Name: django-bob
Version: 1.12.0
Summary: A set of helper tags and templates for using bootstrap in django.
Home-page: http://bob.readthedocs.org/
Author: Radomir Dopieralski
Author-email: devel@sheep.art.pl
License: Apache 2
Keywords: bootstrap django css html
Platform: any
Classifier: Environment :: Web Environment
Classifier: Intended Audience :: Developers
Classifier: License :: OSI Approved :: Apache Software License
Classifier: Operating System :: OS Independent
Classifier: Programming Language :: Python
Classifier: Topic :: Scientific/Engineering :: Human Machine Interfaces
Classifier: Topic :: Software Development :: Libraries :: Python Modules
Classifier: Topic :: Software Development :: User Interfaces
